{
  "type":"FeatureCollection",
  "features": [ {
    "type":"Feature",
    "properties": {
      "name":"Atelier SO",
      "temp":"22.0 C°",
      "hum":"58 %",
      "pm100":20,
      "pm25":16,
      "_umap_options": {
        "color": "Green",
          "popupTemplate": "Table",
          "showLabel": null
        }
    },
    "geometry": {
      "type":"Point",
      "coordinates": [2.335914,48.916965]
    }
  },
  {
    "type":"Feature",
    "properties": {
      "name":"Mairie SO",
      "temp":"24.0 C°",
      "hum":"61 %",
      "pm100":32,
      "pm25":29,
      "_umap_options": {
        "color": "Green",
          "popupTemplate": "Table",
          "showLabel": null
        }
    },
      "geometry": {
        "type":"Point",
        "coordinates": [2.333758,48.912036]
      }
  },
  {
    "type":"Feature",
    "properties": {
      "name": "Michelet / LAndy",
      "temp":"10.0 C°",
      "hum":"88 %",
      "pm100":55,
      "pm25":41,
      "_umap_options": {
        "color": "Red",
          "popupTemplate": "Table",
          "showLabel": null
        }
    },
    "geometry": {
      "type":"Point",
      "coordinates": [2.344208,48.914011]
    }
  } ]
}
